setup.py
pyima/__init__.py
pyima/codec.py
pyima.egg-info/PKG-INFO
pyima.egg-info/SOURCES.txt
pyima.egg-info/dependency_links.txt
pyima.egg-info/not-zip-safe
pyima.egg-info/top_level.txt