Metadata-Version: 1.0
Name: pyima
Version: 0.1
Summary: Python implementation of IMA ADPCM codec.
Home-page: https://github.com/acida/pyima
Author: Alexey Verkhogluad
Author-email: acidaone@gmail.com
License: MIT
Platform: UNKNOWN
